bambic/__init__.py
bambic/__main__.py
bambic-0.1.1.dist-info/METADATA
bambic-0.1.1.dist-info/WHEEL
bambic-0.1.1.dist-info/dependency_links.txt
bambic-0.1.1.dist-info/entry_points.txt
bambic-0.1.1.dist-info/top_level.txt
bambic-0.1.1.dist-info/RECORD
