Metadata-Version: 2.1
Name: bambic
Version: 0.1.1
Summary: WeCode 11th Bambi's second challenge of python programming
Home-page: https://github.com/choonghee-lee/cli-calculator
Author: Choonghee Lee
Author-email: choonghee.dev@gmail.com
License: MIT
Download-URL: https://github.com/choonghee-lee/cli-calculator/archive/master.zip
Platform: UNKNOWN
Classifier: License :: OSI Approved :: MIT License
Classifier: Programming Language :: Python :: 3.7
Requires-Python: >=3.7
Requires-Dist: click
Requires-Dist: click-command-tree
Requires-Dist: click-help-colors
Requires-Dist: click-plugins
